rocklogger/Rocklogger.py
rocklogger/__init__.py
rocklogger-0.8.dist-info/LICENSE.txt
rocklogger-0.8.dist-info/METADATA
rocklogger-0.8.dist-info/WHEEL
rocklogger-0.8.dist-info/top_level.txt
rocklogger-0.8.dist-info/RECORD
