Metadata-Version: 2.2
Name: rocklogger
Version: 0.8
Summary: Rockwool logger with intelligent module filtering
Home-page: https://github.com/rw-MohamedAbouseif/Rocklogger.git
Download-URL: https://github.com/rw-MohamedAbouseif/Rocklogger/archive/refs/tags/v0.8.0.tar.gz
Author: Mohamed Abouseif
Author-email: mohamed.abouseif@rockwool.com
License: MIT
Keywords: Logger,ROCKWOOL,Logging,Filter
Classifier: Development Status :: 5 - Production/Stable
Classifier: Intended Audience :: Developers
Classifier: Topic :: Software Development :: Build Tools
Classifier: License :: OSI Approved :: MIT License
Classifier: Programming Language :: Python :: 3
Classifier: Programming Language :: Python :: 3.4
Classifier: Programming Language :: Python :: 3.5
Classifier: Programming Language :: Python :: 3.6
Classifier: Programming Language :: Python :: 3.7
Classifier: Programming Language :: Python :: 3.8
Classifier: Programming Language :: Python :: 3.9
Classifier: Programming Language :: Python :: 3.10
Classifier: Programming Language :: Python :: 3.11
License-File: LICENSE.txt
Dynamic: author
Dynamic: author-email
Dynamic: classifier
Dynamic: description
Dynamic: description-content-type
Dynamic: download-url
Dynamic: home-page
Dynamic: keywords
Dynamic: license
Dynamic: summary
